signalfixer/__init__.py
signalfixer/timeshift.py
signalfixer/timestamp.py
signalfixer/typing.py
signalfixer/version.py
signalfixer-0.1.5.dist-info/licenses/LICENSE
signalfixer-0.1.5.dist-info/METADATA
signalfixer-0.1.5.dist-info/WHEEL
signalfixer-0.1.5.dist-info/top_level.txt
signalfixer-0.1.5.dist-info/RECORD
