Metadata-Version: 2.4
Name: signalfixer
Version: 0.1.5
Summary: Timestamp treatment, time-shift finder and more.
Home-page: https://github.com/BernatNicolau/signalfixer
Author: Bernat Nicolau
Author-email: bernatnicolaujorda@gmail.com
License: MIT
Classifier: Development Status :: 3 - Alpha
Classifier: Intended Audience :: Developers
Classifier: License :: OSI Approved :: MIT License
Classifier: Topic :: Software Development :: Libraries :: Python Modules
Requires-Python: >=3.7
License-File: LICENSE
Requires-Dist: pandas
Provides-Extra: dev
Requires-Dist: pytest; extra == "dev"
Requires-Dist: sphinx; extra == "dev"
Dynamic: author
Dynamic: author-email
Dynamic: classifier
Dynamic: description
Dynamic: description-content-type
Dynamic: home-page
Dynamic: license
Dynamic: license-file
Dynamic: provides-extra
Dynamic: requires-dist
Dynamic: requires-python
Dynamic: summary
